README.txt
gdal.py
gdalconst.py
gdalnumeric.py
gnm.py
ogr.py
osr.py
setup.cfg
setup.py
GDAL.egg-info/PKG-INFO
GDAL.egg-info/SOURCES.txt
GDAL.egg-info/dependency_links.txt
GDAL.egg-info/not-zip-safe
GDAL.egg-info/top_level.txt
extensions/gdal_array_wrap.cpp
extensions/gdal_wrap.cpp
extensions/gdalconst_wrap.c
extensions/gnm_wrap.cpp
extensions/ogr_wrap.cpp
extensions/osr_wrap.cpp
osgeo/__init__.py
osgeo/gdal.py
osgeo/gdal_array.py
osgeo/gdalconst.py
osgeo/gdalnumeric.py
osgeo/gnm.py
osgeo/ogr.py
osgeo/osr.py
scripts/epsg_tr.py
scripts/esri2wkt.py
scripts/gcps2vec.py
scripts/gcps2wld.py
scripts/gdal2tiles.py
scripts/gdal2xyz.py
scripts/gdal_auth.py
scripts/gdal_calc.py
scripts/gdal_edit.py
scripts/gdal_fillnodata.py
scripts/gdal_merge.py
scripts/gdal_pansharpen.py
scripts/gdal_polygonize.py
scripts/gdal_proximity.py
scripts/gdal_retile.py
scripts/gdal_sieve.py
scripts/gdalchksum.py
scripts/gdalcompare.py
scripts/gdalident.py
scripts/gdalimport.py
scripts/gdalmove.py
scripts/mkgraticule.py
scripts/ogrmerge.py
scripts/pct2rgb.py
scripts/rgb2pct.py